{
  "totalNumberSkippingTests": 0,
  "bugType": "only_fail",
  "totalNumberErroringTests": 1,
  "repo": "bnoi/MAARS",
  "bugCommit": "https://github.com/bnoi/MAARS/compare/00ff075abc01...530524646e78",
  "failingModule": "/root/workspace/bnoi/MAARS/349931833/maars_post",
  "hostname": "spirals-vortex.lille.inria.fr",
  "totalNumberFailingTests": 0,
  "error-types": [
    "java.awt.HeadlessException"
  ],
  "totalNumberRunningTests": 1,
  "failing-test-cases": [
    {
      "className": "[0]",
      "failingMethods": [],
      "erroringMethods": [
        "[0]#calculateIntegratedImgTest[0]"
      ],
      "failures": [
        {
          "failureName": "java.awt.HeadlessException",
          "failureDetail": "\nNo X11 DISPLAY variable was set, but this program performed an operation which requires it.",
          "isError": true
        }
      ],
      "nbFailures": 0,
      "nbErrors": 1
    }
  ]
}