{
  "commits": {},
  "tests": {
    "failingModule": "/scratch/dginelli/workspace/repairnator-repairnator-experiments-asifdxtreme-incubator-servicecomb-java-chassis-348091263-20180302-062207-firstCommit/foundations/foundation-vertx",
    "overallMetrics": {
      "numberRunning": 422,
      "numberPassing": 421,
      "numberFailing": 0,
      "numberErroring": 1,
      "numberSkipping": 0,
      "failures": [
        {
          "failureName": "java.lang.NullPointerException",
          "isError": true,
          "occurrences": 1
        }
      ]
    },
    "failingClasses": [
      {
        "testClass": "org.apache.servicecomb.foundation.vertx.client.tcp.TestTcpClientConnection",
        "numberRunning": 12,
        "numberPassing": 11,
        "numberFailing": 0,
        "numberErroring": 1,
        "numberSkipping": 0
      }
    ],
    "failureDetails": [
      {
        "testClass": "org.apache.servicecomb.foundation.vertx.client.tcp.TestTcpClientConnection",
        "testMethod": "send_inWorkingStatus",
        "failureName": "java.lang.NullPointerException",
        "isError": true
      }
    ]
  },
  "projectMetrics": {
    "numberModules": 62,
    "numberPlugins": 0,
    "numberSourceFiles": 829,
    "numberTestFiles": 500,
    "numberLibrariesFailingModule": 66,
    "numberLines": 0
  },
  "builds": {},
  "reproductionBuggyBuild": {
    "reproductionDateBeginning": "Mar 18, 2020 10:31:19 AM",
    "reproductionDateEnd": "Mar 18, 2020 12:16:47 PM",
    "machineInfo": {
      "numberCPU": 1,
      "freeMemory": 48020840,
      "totalMemory": 118300672
    },
    "totalDuration": 6324,
    "processDurations": {
      "cloning": {
        "nbSteps": 0,
        "totalDuration": 0,
        "stepNames": [],
        "stepDurations": []
      },
      "building": {
        "nbSteps": 3,
        "totalDuration": 3,
        "stepNames": [
          "ComputeSourceDir",
          "ComputeTestDir",
          "CheckoutPatchedBuild"
        ],
        "stepDurations": [
          0,
          3,
          0
        ]
      },
      "testing": {
        "nbSteps": 0,
        "totalDuration": 0,
        "stepNames": [],
        "stepDurations": []
      },
      "fixing": {
        "nbSteps": 1,
        "totalDuration": 6002,
        "stepNames": [
          "AstorJKali"
        ],
        "stepDurations": [
          6002
        ]
      }
    },
    "projectRootPomPath": "/scratch/dginelli/workspace/repairnator-repairnator-experiments-asifdxtreme-incubator-servicecomb-java-chassis-348091263-20180302-062207-firstCommit/pom.xml"
  },
  "repository": {
    "githubId": 0,
    "isFork": false,
    "original": {
      "name": "",
      "githubId": 0,
      "url": ""
    },
    "isPullRequest": false,
    "pullRequestId": 0
  },
  "patchDiff": {
    "files": {
      "numberAdded": 0,
      "numberChanged": 0,
      "numberDeleted": 0
    },
    "lines": {
      "numberAdded": 0,
      "numberDeleted": 0
    }
  }
}