{
  "totalNumberSkippingTests": 0,
  "bugType": "only_fail",
  "totalNumberErroringTests": 1,
  "repo": "tgouvea/springboot-example",
  "bugCommit": "https://github.com/tgouvea/springboot-example/compare/4c4f75496882...57a1b180fd41",
  "failingModule": "/root/workspace/tgouvea/springboot-example/349508102",
  "hostname": "spirals-vortex.lille.inria.fr",
  "totalNumberFailingTests": 0,
  "error-types": [
    "java.lang.IllegalStateException"
  ],
  "totalNumberRunningTests": 1,
  "failing-test-cases": [
    {
      "className": "com.tiagogouvea.api.SpringbootExampleApplicationTests",
      "failingMethods": [],
      "erroringMethods": [
        "com.tiagogouvea.api.SpringbootExampleApplicationTests#contextLoads"
      ],
      "failures": [
        {
          "failureName": "java.lang.IllegalStateException",
          "failureDetail": "Failed to load ApplicationContext",
          "isError": true
        }
      ],
      "nbFailures": 0,
      "nbErrors": 1
    }
  ]
}